Workbook

Sheet Leia-me
A1: Base de Dados - Recursos Repassados às UPAs de Feira de Santana/BA
A2: Municipal | Estadual | Federal — Série histórica 2021-2026
B4: OBJETIVO
B5: Consolidar, em uma única base relacional, os recursos municipais, estaduais e federais repassados para a gestão das Unidades de Pronto Atendimento (UPA) de Feira de Santana/BA, permitindo montar dashboards e, futuramente, alimentar um aplicativo/API de acompanhamento orçamentário e financeiro.
B7: COMO ESTA PASTA DE TRABALHO ESTÁ ORGANIZADA (modelo estrela)
B8: • dim_UPA — cadastro das unidades (gestão municipal, estadual e/ou OSS).
B9: • dim_Fonte_Recurso — esfera de governo, órgão repassador e programa/instrumento.
B10: • dim_Bloco_Financiamento — blocos de financiamento do SUS (Custeio, Investimento, Emenda Parlamentar etc.).
B11: • dim_Categoria_Despesa — natureza do gasto (pessoal, custeio, investimento, obras...).
B12: • dim_Tempo — calendário ano/mês/trimestre/semestre para facilitar filtros em dashboards.
B13: • Fato_Repasses — tabela fato (uma linha por UPA + Fonte + Bloco + Mês). É AQUI que os valores reais entram.
B14: • Indicadores_Dashboard — KPIs calculados automaticamente a partir da tabela fato (fórmulas SUMIFS).
B15: • Fontes_Oficiais — onde buscar os números reais para preencher a base.
B16: • Dicionario_Dados — descrição de cada campo, tipo e regra de preenchimento.
... B47: 'recursos repassados às UPAs de Feira de Santana, por esfera, mês a mês, últimos 5 anos'.

Sheet Dicionario_Dados
A1: Dicionário de Dados
A3: Tabela | B3: Campo | C3: Tipo | D3: Descrição / Regra | E3: Domínio (valores aceitos)
A4: dim_UPA | B4: id_UPA | C4: Texto (PK) | D4: Identificador único da unidade | E4: UPA-01, UPA-02...
A5: dim_UPA | B5: Nome_UPA | C5: Texto | D5: Nome oficial da UPA | E5: -
A6: dim_UPA | B6: Tipo_Gestao | C6: Texto | D6: Ente responsável pela gestão direta | E6: Municipal / Estadual (OSS) / Consórcio
A7: dim_UPA | B7: Porte | C7: Texto | D7: Porte da unidade conforme portaria MS | E7: Porte I / II / III
A8: dim_Fonte_Recurso | B8: id_Fonte | C8: Texto (PK) | D8: Identificador da fonte de recurso | E8: FR-01, FR-02...
A9: dim_Fonte_Recurso | B9: Esfera | C9: Texto | D9: Nível federativo de origem do recurso | E9: Municipal / Estadual / Federal
A10: dim_Fonte_Recurso | B10: Orgao_Repassador | C10: Texto | D10: Órgão/fundo que efetua o repasse | E10: -
A11: dim_Bloco_Financiamento | B11: id_Bloco | C11: Texto (PK) | D11: Identificador do bloco de financiamento SUS | E11: BF-01, BF-02...
A12: dim_Categoria_Despesa | B12: id_Categoria | C12: Texto (PK) | D12: Identificador da natureza de despesa | E12: CD-01, CD-02...
A13: dim_Tempo | B13: id_Tempo | C13: Texto (PK) | D13: Chave ano-mês | E13: AAAA-MM
A14: Fato_Repasses | B14: id_Lancamento | C14: Número (PK) | D14: Sequencial único do lançamento | E14: Autoincremento
... A21: Fato_Repasses | B21: Fonte_Dado | C21: Texto/URL | D21: Referência/documento oficial de onde o valor foi extraído | E21: Link ou identificação do documento

Sheet dim_UPA
A1: dim_UPA — Cadastro das Unidades de Pronto Atendimento
A2: Complete/confirme os dados junto ao CNES-DATASUS e à Secretaria Municipal de Saúde
A3: id_UPA | B3: Nome_UPA | C3: CNES/CNPJ | D3: Tipo_Gestao | E3: Endereço | F3: Porte | G3: Ano_Inauguração | H3: Leitos | I3: Telefone | J3: Observações / Fonte
A4: UPA-01 | B4: UPA Feira de Santana (UPA 24h) | C4: 14.284.483/0002-99 (CNPJ da unidade) | D4: Estadual — Contrato de Gestão nº 052/2018 com OSS. Gestora até ~2023: INTS (Instituto Nacional de Tecnologia e Saúde). Gestora identificada em registros mais recentes (2024-2025): S3 Gestão em Saúde / Associação de Proteção à Maternidade e Infância Ubaíra, CNPJ 14.284.483/0001-08 — confirmar data exata da transição de OSS junto à SESAB. | E4: Av. Eduardo Fróes da Mota, s/n, 35º BI, Feira de Santana/BA | F4: Porte III | G4: 2016 | H4: 24 | I4: (75) 3471-3705 | J4: Fonte: SESAB (saude.ba.gov.br); razões contábeis publicadas em upadefeira.ints.org.br/transparencia; cadastro atual em s3saude.org.br. Confirmar CNES junto ao CNES-DATASUS.
A5: UPA-02 | B5: UPA Elisabete Dias Marques (UPA Queimadinha) | C5: A confirmar no CNES-DATASUS | D5: Municipal — Secretaria Municipal de Saúde (SMS), gestão por Contrato de Gestão com a OSS INSAÚDE (Instituto Nacional de Pesquisa e Gestão em Saúde) desde 02/05/2018. Contrato vigente: nº 437/2024 (origem: Chamada Pública nº 3-2023-CHP), prorrogado pelo Termo Aditivo nº 245-2026-11AC até 18/06/2027. | E5: Bairro Queimadinha, Feira de Santana/BA | F5: Porte II | G5: 2018 | H5: Capacidade: até 4.500 atendimentos/mês (1.700 m²) | I5: A confirmar | J5: Fonte: Jornal Grande Bahia (dez/2024), Bahia na Política e Blog do Velame (jun/2026) — reportagens sobre o contrato de gestão publicado no Diário Oficial do Município; Prefeitura de Feira de Santana (matéria institucional).
A6: UPA-03 | B6: 3ª unidade cadastrada no CNES (nome a confirmar) | C6: A confirmar | D6: A confirmar | E6: A confirmar | F6: A confirmar | G6: A confirmar | H6: A confirmar | I6: A confirmar | J6: O CNES-DATASUS/PerguntaSaúde indica 3 UPAs cadastradas em Feira de Santana; esta 3ª unidade deve ser identificada e cadastrada pela equipe (ex.: unidade de referência regional adicional, se houver).

Sheet dim_Fonte_Recurso
A1: dim_Fonte_Recurso — Esferas e órgãos repassadores
A3: id_Fonte | B3: Esfera | C3: Orgao_Repassador | D3: Programa / Instrumento típico | E3: Observações
A4: FR-01 | B4: Federal | C4: Ministério da Saúde / Fundo Nacional de Saúde (FNS) | D4: Transferência Fundo a Fundo (Bloco de Custeio e de Investimento) / InvestSUS | E4: Consultar valores em painelms.saude.gov.br (Consulta Gerencial FNS) e antigo.saude.gov.br/repasses-financeiros
A5: FR-02 | B5: Federal | C5: Emendas Parlamentares (individuais/bancada) via FNS | D5: Transferência especial ou Fundo a Fundo, processada no InvestSUS | E5: Publicadas em Portarias do DOU; registrar nº da portaria em Numero_Documento
A6: FR-03 | B6: Estadual | C6: Governo do Estado da Bahia / Secretaria da Saúde (SESAB) / Fundo Estadual de Saúde | D6: Contrato de Gestão com Organização Social de Saúde (ex.: INTS) para a UPA estadual | E6: Demonstrativos financeiros da OSS costumam ser publicados no site da própria unidade/OSS
A7: FR-04 | B7: Municipal | C7: Prefeitura Municipal de Feira de Santana / Fundo Municipal de Saúde | D7: Recursos próprios do Tesouro Municipal (contrapartida e custeio) | E7: Consultar Portal da Transparência do Município e LOA/LDO/PPA da Secretaria de Saúde

Sheet dim_Bloco_Financiamento
A1: dim_Bloco_Financiamento — Blocos de financiamento do SUS
A3: id_Bloco | B3: Nome_Bloco | C3: Descrição
A4: BF-01 | B4: Bloco de Manutenção das Ações e Serviços Públicos de Saúde (Custeio) | C4: Custeio corrente: pessoal terceirizado, medicamentos, materiais, manutenção — Portaria GM/MS nº 3.992/2017 e atualizações
A5: BF-02 | B5: Bloco de Investimento na Rede de Serviços Públicos de Saúde | C5: Obras, reformas, equipamentos e aquisição de bens permanentes
A6: BF-03 | B6: Emenda Parlamentar | C6: Recursos federais de emendas individuais/de bancada, processados via InvestSUS/FNS
A7: BF-04 | B7: Contrato de Gestão (OSS) | C7: Repasse regular (estadual ou municipal) à Organização Social de Saúde que gere a unidade, mediante contrato de gestão
A8: BF-05 | B8: Recursos Próprios (Tesouro Municipal) | C8: Contrapartida e custeio com recursos do orçamento próprio do município

Sheet dim_Categoria_Despesa
A1: dim_Categoria_Despesa — Natureza do gasto
A3: id_Categoria | B3: Nome_Categoria | C3: Exemplos
A4: CD-01 | B4: Pessoal e Encargos | C4: Equipe assistencial e administrativa, plantonistas, encargos sociais
A5: CD-02 | B5: Custeio Operacional | C5: Medicamentos, materiais médico-hospitalares, insumos, exames
A6: CD-03 | B6: Manutenção Predial e Equipamentos | C6: Manutenção corretiva/preventiva de estrutura e equipamentos
A7: CD-04 | B7: Investimento / Aquisição de Equipamentos | C7: Compra de bens permanentes, equipamentos médicos
A8: CD-05 | B8: Obras e Reformas | C8: Ampliação, reforma ou construção de unidade
A9: CD-06 | B9: Serviços Terceirizados de Gestão | C9: Taxa de administração/gestão da OSS, quando aplicável

Sheet dim_Tempo
A1: dim_Tempo — Calendário (2021-2026)
A3: id_Tempo | B3: Ano | C3: Mes | D3: Nome_Mes | E3: Trimestre | F3: Semestre
A4: 2021-01 | B4: 2021 | C4: 1 | D4: Janeiro | E4: T1 | F4: S1
A5: 2021-02 | B5: 2021 | C5: 2 | D5: Fevereiro | E5: T1 | F5: S1
A6: 2021-03 | B6: 2021 | C6: 3 | D6: Março | E6: T1 | F6: S1
A7: 2021-04 | B7: 2021 | C7: 4 | D7: Abril | E7: T2 | F7: S1
A8: 2021-05 | B8: 2021 | C8: 5 | D8: Maio | E8: T2 | F8: S1
A9: 2021-06 | B9: 2021 | C9: 6 | D9: Junho | E9: T2 | F9: S1
A10: 2021-07 | B10: 2021 | C10: 7 | D10: Julho | E10: T3 | F10: S2
A11: 2021-08 | B11: 2021 | C11: 8 | D11: Agosto | E11: T3 | F11: S2
A12: 2021-09 | B12: 2021 | C12: 9 | D12: Setembro | E12: T3 | F12: S2
A13: 2021-10 | B13: 2021 | C13: 10 | D13: Outubro | E13: T4 | F13: S2
A14: 2021-11 | B14: 2021 | C14: 11 | D14: Novembro | E14: T4 | F14: S2
A15: 2021-12 | B15: 2021 | C15: 12 | D15: Dezembro | E15: T4 | F15: S2
... A75: 2026-12 | B75: 2026 | C75: 12 | D75: Dezembro | E75: T4 | F75: S2

Sheet Fato_Repasses
A1: Fato_Repasses — Lançamentos de repasses e execução financeira por UPA
A2: Linhas em cinza/itálico (topo) = dados REAIS localizados em fontes públicas nesta pesquisa. Linhas com fundo amarelo = para a equipe preencher.
A3: id_Lancamento | B3: Ano | C3: Mes | D3: id_UPA | E3: id_Fonte | F3: id_Bloco | G3: id_Categoria | H3: Instrumento | I3: Numero_Documento | J3: Valor_Previsto (R$) | K3: Valor_Repassado (R$) | L3: Valor_Empenhado (R$) | M3: Valor_Liquidado (R$) | N3: Valor_Pago (R$) | O3: % Execução (Pago/Repassado) | P3: Fonte_Dado / Observações
A4: 1 | B4: 2022 | C4: 8 | D4: UPA-01 | E4: FR-03 | F4: BF-04 | G4: CD-02 | H4: Contrato de Gestão | I4: Doc. 000000002928 - Competência 08/2022 - CTR 052/2018 | K4: 1404927.7 | O4: =IFERROR(N4/K4,"") -> 0 | P4: REAL. Valor repassado pelo Fundo Estadual de Saúde à OSS gestora (INTS) referente à competência do mês. Empenhado/liquidado/pago não constam no razão consultado. Fonte: Razão contábil Jun/2023, upadefeira.ints.org.br/transparencia
A5: 2 | B5: 2022 | C5: 9 | D5: UPA-01 | E5: FR-03 | F5: BF-04 | G5: CD-02 | H5: Contrato de Gestão | I5: Doc. 000000002962 - Competência 09/2022 - CTR 052/2018 | K5: 1405344.2 | O5: =IFERROR(N5/K5,"") -> 0 | P5: REAL. Idem acima. Fonte: Razão contábil Jun/2023, upadefeira.ints.org.br/transparencia
A6: 3 | B6: 2022 | C6: 10 | D6: UPA-01 | E6: FR-03 | F6: BF-04 | G6: CD-02 | H6: Contrato de Gestão | I6: Doc. 000000002995 - Competência 10/2022 - CTR 052/2018 | K6: 1049435.6 | O6: =IFERROR(N6/K6,"") -> 0 | P6: REAL (valor abaixo da média — possível repasse parcial no mês; confirmar com a OSS/SESAB). Fonte: Razão contábil Jun/2023, upadefeira.ints.org.br/transparencia
A7: 4 | B7: 2022 | C7: 11 | D7: UPA-01 | E7: FR-03 | F7: BF-04 | G7: CD-02 | H7: Contrato de Gestão | I7: Doc. 000000003012 - Competência 11/2022 - CTR 052/2018 | K7: 1401291.1 | O7: =IFERROR(N7/K7,"") -> 0 | P7: REAL. Fonte: Razão contábil Jun/2023, upadefeira.ints.org.br/transparencia
A8: 5 | B8: 2022 | C8: 12 | D8: UPA-01 | E8: FR-03 | F8: BF-04 | G8: CD-02 | H8: Contrato de Gestão | I8: Doc. 000000003043 - Competência 12/2022 - CTR 052/2018 | K8: 1401095.1 | O8: =IFERROR(N8/K8,"") -> 0 | P8: REAL. Fonte: Razão contábil Jun/2023, upadefeira.ints.org.br/transparencia
A9: 6 | B9: 2023 | C9: 1 | D9: UPA-01 | E9: FR-03 | F9: BF-04 | G9: CD-02 | H9: Contrato de Gestão | I9: Doc. 000000003053 - Competência 01/2023 - CTR 052/2018 | K9: 960786.27 | O9: =IFERROR(N9/K9,"") -> 0 | P9: REAL (valor abaixo da média — possível repasse parcial no mês; confirmar com a OSS/SESAB). Fonte: Razão contábil Jun/2023, upadefeira.ints.org.br/transparencia
A10: 7 | B10: 2023 | C10: 2 | D10: UPA-01 | E10: FR-03 | F10: BF-04 | G10: CD-02 | H10: Contrato de Gestão | I10: Doc. 000000003063 - Competência 02/2023 - CTR 052/2018 | K10: 1315661.7 | O10: =IFERROR(N10/K10,"") -> 0 | P10: REAL. Fonte: Razão contábil Jun/2023, upadefeira.ints.org.br/transparencia
A11: 8 | B11: 2026 | C11: 6 | D11: UPA-02 | E11: FR-04 | F11: BF-04 | G11: CD-02 | H11: Contrato de Gestão | I11: Termo Aditivo nº 245-2026-11AC ao Contrato nº 437/2024 (SMS/INSAÚDE) | J11: 1235917 | O11: =IFERROR(N11/K11,"") | P11: VALOR CONTRATUAL (não é o repasse mensal efetivamente apurado): contrato de gestão renovado em R$ 14.831.003,93/ano (÷12 meses), vigência 18/06/2026 a 18/06/2027. Repasse mensal real pode variar; confirmar execução junto ao Fundo Municipal de Saúde. Fonte: Blog do Velame e Bahia na Política (jun/2026), Diário Oficial do Município.
A12: =IF(D12="","",ROW()-11) | O12: =IFERROR(N12/K12,"")
A13: =IF(D13="","",ROW()-11) | O13: =IFERROR(N13/K13,"")
A14: =IF(D14="","",ROW()-11) | O14: =IFERROR(N14/K14,"")
A15: =IF(D15="","",ROW()-11) | O15: =IFERROR(N15/K15,"")
A16: =IF(D16="","",ROW()-11) | O16: =IFERROR(N16/K16,"")
A17: =IF(D17="","",ROW()-11) | O17: =IFERROR(N17/K17,"")
A18: =IF(D18="","",ROW()-11) | O18: =IFERROR(N18/K18,"")
A19: =IF(D19="","",ROW()-11) | O19: =IFERROR(N19/K19,"")
A20: =IF(D20="","",ROW()-11) | O20: =IFERROR(N20/K20,"")
A21: =IF(D21="","",ROW()-11) | O21: =IFERROR(N21/K21,"")
A22: =IF(D22="","",ROW()-11) | O22: =IFERROR(N22/K22,"")
A23: =IF(D23="","",ROW()-11) | O23: =IFERROR(N23/K23,"")
... A311: =IF(D311="","",ROW()-11) | O311: =IFERROR(N311/K311,"")

Sheet Indicadores_Dashboard
A1: Indicadores_Dashboard — KPIs calculados a partir de Fato_Repasses
A2: Estes quadros recalculam automaticamente conforme a aba Fato_Repasses é preenchida (fórmulas SUMIFS).
A4: 1) Total repassado por ano e por esfera (R$)
A5: Ano | B5: Municipal | C5: Estadual | D5: Federal | E5: Total Ano
A6: 2021 | B6: =SUMPRODUCT(Fato_Repasses!$K$4:$K$311*(IFERROR(INDEX(dim_Fonte_Recurso!$B$4:$B$7,MATCH(Fato_Repasses!$E$4:$E$311,dim_Fonte_Recurso!$A$4:$A$7,0)),"")="Municipal")*(Fato_Repasses!$B$4:$B$311=2021)) -> 0 | C6: =SUMPRODUCT(Fato_Repasses!$K$4:$K$311*(IFERROR(INDEX(dim_Fonte_Recurso!$B$4:$B$7,MATCH(Fato_Repasses!$E$4:$E$311,dim_Fonte_Recurso!$A$4:$A$7,0)),"")="Estadual")*(Fato_Repasses!$B$4:$B$311=2021)) -> 0 | D6: =SUMPRODUCT(Fato_Repasses!$K$4:$K$311*(IFERROR(INDEX(dim_Fonte_Recurso!$B$4:$B$7,MATCH(Fato_Repasses!$E$4:$E$311,dim_Fonte_Recurso!$A$4:$A$7,0)),"")="Federal")*(Fato_Repasses!$B$4:$B$311=2021)) -> 0 | E6: =SUM(B6:D6) -> 0
A7: 2022 | B7: =SUMPRODUCT(Fato_Repasses!$K$4:$K$311*(IFERROR(INDEX(dim_Fonte_Recurso!$B$4:$B$7,MATCH(Fato_Repasses!$E$4:$E$311,dim_Fonte_Recurso!$A$4:$A$7,0)),"")="Municipal")*(Fato_Repasses!$B$4:$B$311=2022)) -> 0 | C7: =SUMPRODUCT(Fato_Repasses!$K$4:$K$311*(IFERROR(INDEX(dim_Fonte_Recurso!$B$4:$B$7,MATCH(Fato_Repasses!$E$4:$E$311,dim_Fonte_Recurso!$A$4:$A$7,0)),"")="Estadual")*(Fato_Repasses!$B$4:$B$311=2022)) -> 6662093.7 | D7: =SUMPRODUCT(Fato_Repasses!$K$4:$K$311*(IFERROR(INDEX(dim_Fonte_Recurso!$B$4:$B$7,MATCH(Fato_Repasses!$E$4:$E$311,dim_Fonte_Recurso!$A$4:$A$7,0)),"")="Federal")*(Fato_Repasses!$B$4:$B$311=2022)) -> 0 | E7: =SUM(B7:D7) -> 6662093.7
A8: 2023 | B8: =SUMPRODUCT(Fato_Repasses!$K$4:$K$311*(IFERROR(INDEX(dim_Fonte_Recurso!$B$4:$B$7,MATCH(Fato_Repasses!$E$4:$E$311,dim_Fonte_Recurso!$A$4:$A$7,0)),"")="Municipal")*(Fato_Repasses!$B$4:$B$311=2023)) -> 0 | C8: =SUMPRODUCT(Fato_Repasses!$K$4:$K$311*(IFERROR(INDEX(dim_Fonte_Recurso!$B$4:$B$7,MATCH(Fato_Repasses!$E$4:$E$311,dim_Fonte_Recurso!$A$4:$A$7,0)),"")="Estadual")*(Fato_Repasses!$B$4:$B$311=2023)) -> 2276447.9 | D8: =SUMPRODUCT(Fato_Repasses!$K$4:$K$311*(IFERROR(INDEX(dim_Fonte_Recurso!$B$4:$B$7,MATCH(Fato_Repasses!$E$4:$E$311,dim_Fonte_Recurso!$A$4:$A$7,0)),"")="Federal")*(Fato_Repasses!$B$4:$B$311=2023)) -> 0 | E8: =SUM(B8:D8) -> 2276447.9
A9: 2024 | B9: =SUMPRODUCT(Fato_Repasses!$K$4:$K$311*(IFERROR(INDEX(dim_Fonte_Recurso!$B$4:$B$7,MATCH(Fato_Repasses!$E$4:$E$311,dim_Fonte_Recurso!$A$4:$A$7,0)),"")="Municipal")*(Fato_Repasses!$B$4:$B$311=2024)) -> 0 | C9: =SUMPRODUCT(Fato_Repasses!$K$4:$K$311*(IFERROR(INDEX(dim_Fonte_Recurso!$B$4:$B$7,MATCH(Fato_Repasses!$E$4:$E$311,dim_Fonte_Recurso!$A$4:$A$7,0)),"")="Estadual")*(Fato_Repasses!$B$4:$B$311=2024)) -> 0 | D9: =SUMPRODUCT(Fato_Repasses!$K$4:$K$311*(IFERROR(INDEX(dim_Fonte_Recurso!$B$4:$B$7,MATCH(Fato_Repasses!$E$4:$E$311,dim_Fonte_Recurso!$A$4:$A$7,0)),"")="Federal")*(Fato_Repasses!$B$4:$B$311=2024)) -> 0 | E9: =SUM(B9:D9) -> 0
A10: 2025 | B10: =SUMPRODUCT(Fato_Repasses!$K$4:$K$311*(IFERROR(INDEX(dim_Fonte_Recurso!$B$4:$B$7,MATCH(Fato_Repasses!$E$4:$E$311,dim_Fonte_Recurso!$A$4:$A$7,0)),"")="Municipal")*(Fato_Repasses!$B$4:$B$311=2025)) -> 0 | C10: =SUMPRODUCT(Fato_Repasses!$K$4:$K$311*(IFERROR(INDEX(dim_Fonte_Recurso!$B$4:$B$7,MATCH(Fato_Repasses!$E$4:$E$311,dim_Fonte_Recurso!$A$4:$A$7,0)),"")="Estadual")*(Fato_Repasses!$B$4:$B$311=2025)) -> 0 | D10: =SUMPRODUCT(Fato_Repasses!$K$4:$K$311*(IFERROR(INDEX(dim_Fonte_Recurso!$B$4:$B$7,MATCH(Fato_Repasses!$E$4:$E$311,dim_Fonte_Recurso!$A$4:$A$7,0)),"")="Federal")*(Fato_Repasses!$B$4:$B$311=2025)) -> 0 | E10: =SUM(B10:D10) -> 0
A11: 2026 | B11: =SUMPRODUCT(Fato_Repasses!$K$4:$K$311*(IFERROR(INDEX(dim_Fonte_Recurso!$B$4:$B$7,MATCH(Fato_Repasses!$E$4:$E$311,dim_Fonte_Recurso!$A$4:$A$7,0)),"")="Municipal")*(Fato_Repasses!$B$4:$B$311=2026)) -> 0 | C11: =SUMPRODUCT(Fato_Repasses!$K$4:$K$311*(IFERROR(INDEX(dim_Fonte_Recurso!$B$4:$B$7,MATCH(Fato_Repasses!$E$4:$E$311,dim_Fonte_Recurso!$A$4:$A$7,0)),"")="Estadual")*(Fato_Repasses!$B$4:$B$311=2026)) -> 0 | D11: =SUMPRODUCT(Fato_Repasses!$K$4:$K$311*(IFERROR(INDEX(dim_Fonte_Recurso!$B$4:$B$7,MATCH(Fato_Repasses!$E$4:$E$311,dim_Fonte_Recurso!$A$4:$A$7,0)),"")="Federal")*(Fato_Repasses!$B$4:$B$311=2026)) -> 0 | E11: =SUM(B11:D11) -> 0
A12: Total | B12: =SUM(B6:B11) -> 0 | C12: =SUM(C6:C11) -> 8938541.6 | D12: =SUM(D6:D11) -> 0 | E12: =SUM(E6:E11) -> 8938541.6
A15: 2) Total repassado por UPA (todo o período carregado)
A16: UPA | B16: Total Repassado (R$) | C16: Total Pago (R$) | D16: % Execução
A17: =IFERROR(INDEX(dim_UPA!$B$4:$B$6,1),"") -> UPA Feira de Santana (UPA 24h) | B17: =SUMIF(Fato_Repasses!$D$4:$D$311,dim_UPA!$A$4,Fato_Repasses!$K$4:$K$311) -> 8938541.6 | C17: =SUMIF(Fato_Repasses!$D$4:$D$311,dim_UPA!$A$4,Fato_Repasses!$N$4:$N$311) -> 0 | D17: =IFERROR(C17/B17,"") -> 0
A18: =IFERROR(INDEX(dim_UPA!$B$4:$B$6,2),"") -> UPA Elisabete Dias Marques (UPA Queimadinha) | B18: =SUMIF(Fato_Repasses!$D$4:$D$311,dim_UPA!$A$5,Fato_Repasses!$K$4:$K$311) -> 0 | C18: =SUMIF(Fato_Repasses!$D$4:$D$311,dim_UPA!$A$5,Fato_Repasses!$N$4:$N$311) -> 0 | D18: =IFERROR(C18/B18,"")
A19: =IFERROR(INDEX(dim_UPA!$B$4:$B$6,3),"") -> 3ª unidade cadastrada no CNES (nome a confirmar) | B19: =SUMIF(Fato_Repasses!$D$4:$D$311,dim_UPA!$A$6,Fato_Repasses!$K$4:$K$311) -> 0 | C19: =SUMIF(Fato_Repasses!$D$4:$D$311,dim_UPA!$A$6,Fato_Repasses!$N$4:$N$311) -> 0 | D19: =IFERROR(C19/B19,"")
A22: 3) Participação (%) de cada esfera no total repassado
A23: Esfera | B23: Total (R$) | C23: % do Total
A24: Municipal | B24: =SUMPRODUCT(Fato_Repasses!$K$4:$K$311*(IFERROR(INDEX(dim_Fonte_Recurso!$B$4:$B$7,MATCH(Fato_Repasses!$E$4:$E$311,dim_Fonte_Recurso!$A$4:$A$7,0)),"")="Municipal")) -> 0 | C24: =IFERROR(B24/SUM($B$24:$B$26),"") -> 0
A25: Estadual | B25: =SUMPRODUCT(Fato_Repasses!$K$4:$K$311*(IFERROR(INDEX(dim_Fonte_Recurso!$B$4:$B$7,MATCH(Fato_Repasses!$E$4:$E$311,dim_Fonte_Recurso!$A$4:$A$7,0)),"")="Estadual")) -> 8938541.6 | C25: =IFERROR(B25/SUM($B$25:$B$27),"") -> 1
A26: Federal | B26: =SUMPRODUCT(Fato_Repasses!$K$4:$K$311*(IFERROR(INDEX(dim_Fonte_Recurso!$B$4:$B$7,MATCH(Fato_Repasses!$E$4:$E$311,dim_Fonte_Recurso!$A$4:$A$7,0)),"")="Federal")) -> 0 | C26: =IFERROR(B26/SUM($B$26:$B$28),"")

Sheet Fontes_Oficiais
A1: Fontes_Oficiais — Onde buscar os dados reais para preencher a base
A3: Esfera / Sistema | B3: O que traz e como usar | C3: Link
A4: Federal — FNS Consulta Gerencial | B4: Repasses fundo a fundo por município, bloco de financiamento e competência (mensal). Filtrar por Bahia > Feira de Santana. | C4: https://painelms.saude.gov.br/extensions/Portal_Gerencial/Portal_Gerencial.html
A5: Federal — Repasses Financeiros / Fundo Nacional de Saúde | B5: Portal institucional do FNS com blocos de custeio e investimento, SISMOB (obras) e InvestSUS (emendas/propostas). | C5: https://antigo.saude.gov.br/repasses-financeiros
A6: Federal — Portal da Transparência (Governo Federal) | B6: Transferências de recursos federais ao município, incluindo saúde, por ano. | C6: https://portaldatransparencia.gov.br
A7: Estadual — SESAB / Fundo Estadual de Saúde | B7: Contrato de gestão nº 052/2018 da UPA estadual. Demonstrativos financeiros (Razão/Balancete/Diário) mensais publicados pela OSS gestora — usados nesta pesquisa para localizar valores reais de ago/2022 a fev/2023. | C7: https://upadefeira.ints.org.br/transparencia/
A8: Estadual — S3 Gestão em Saúde (OSS atual) | B8: Página de transparência da atual gestora da UPA Feira de Santana, com relatórios gerenciais de produção mensal (2024-2025). | C8: https://s3saude.org.br/unidade-de-pronto-atendimento-de-feira-de-santana-upa-24h-transparencia/
A9: Municipal — Diário Oficial do Município | B9: Publica os contratos de gestão e termos aditivos (ex.: Contrato nº 437/2024 e Termo Aditivo nº 245-2026-11AC, UPA Queimadinha/INSAÚDE) com os valores contratuais anuais. | C9: https://diariooficial.feiradesantana.ba.gov.br
A10: Estadual — Portal da Transparência da Bahia | B10: Execução orçamentária estadual por unidade gestora/programa de saúde. | C10: https://www.transparencia.ba.gov.br
A11: Municipal — Portal da Transparência de Feira de Santana | B11: Execução orçamentária municipal, despesas por secretaria/fundo, incluindo Fundo Municipal de Saúde. | C11: http://www.feiradesantana.ba.gov.br
A12: Municipal/Estadual/Federal — SIOPS | B12: Sistema de Informações sobre Orçamentos Públicos em Saúde: receitas e despesas em saúde por município, série histórica. | C12: https://www.gov.br/saude
A13: Cadastro das unidades — CNES/DATASUS | B13: Cadastro Nacional de Estabelecimentos de Saúde: confirma nome oficial, CNES, porte e leitos de cada UPA de Feira de Santana. | C13: https://cnes.datasus.gov.br
A14: Controle interno — Câmara Municipal / TCM-BA | B14: Pareceres, prestações de contas e auditorias sobre a aplicação dos recursos da saúde no município. | C14: https://www.tcm.ba.gov.br
